{
  "id": "demo-seongnam-night",
  "title": "성남시 17세 최중증 발달장애인 · 야간 보호자 응급입원",
  "region": "성남시 분당구",
  "homeDong": "정자동",
  "occurredAt": "21:30",
  "inputText": "오늘 21시 30분경, 분당구 정자동에 사는 17세 최중증 발달장애인 A의 어머니(주 보호자)가 갑자기 쓰러져 응급실에 입원했습니다. 아버지는 지방 출장 중이라 당장 돌볼 가족이 없습니다. A는 평소 장애인활동지원 서비스를 이용 중이고, 의사소통이 거의 안 되며 야간에 불안과 자해 위험이 있어 혼자 두기 어렵습니다. 저녁 복약도 챙겨야 합니다. 최소 내일 오전까지는 대체 돌봄이 필요한 상황입니다.",
  "guideExamples": [
    "독거 치매 어르신 주간보호 차량 사고로 당일 돌봄 중단",
    "중증 지체장애인 활동지원사 야간 결근으로 새벽 돌봄 공백",
    "퇴원 예정 환자 보호자 부재로 72시간 내 재가돌봄 연계 필요"
  ]
}
